odoo8_addon_sale_allotment-8.0.1.1.0.99.dev20-py2.7-nspkg.pth
odoo8_addon_sale_allotment-8.0.1.1.0.99.dev20.dist-info/DESCRIPTION.rst
odoo8_addon_sale_allotment-8.0.1.1.0.99.dev20.dist-info/METADATA
odoo8_addon_sale_allotment-8.0.1.1.0.99.dev20.dist-info/RECORD
odoo8_addon_sale_allotment-8.0.1.1.0.99.dev20.dist-info/WHEEL
odoo8_addon_sale_allotment-8.0.1.1.0.99.dev20.dist-info/metadata.json
odoo8_addon_sale_allotment-8.0.1.1.0.99.dev20.dist-info/namespace_packages.txt
odoo8_addon_sale_allotment-8.0.1.1.0.99.dev20.dist-info/top_level.txt
odoo_addons/sale_allotment/README.rst
odoo_addons/sale_allotment/__init__.py
odoo_addons/sale_allotment/__openerp__.py
odoo_addons/sale_allotment/i18n/ca.po
odoo_addons/sale_allotment/i18n/de.po
odoo_addons/sale_allotment/i18n/es.po
odoo_addons/sale_allotment/i18n/es_AR.po
odoo_addons/sale_allotment/i18n/es_MX.po
odoo_addons/sale_allotment/i18n/fi.po
odoo_addons/sale_allotment/i18n/fr.po
odoo_addons/sale_allotment/i18n/hr.po
odoo_addons/sale_allotment/i18n/it.po
odoo_addons/sale_allotment/i18n/pt.po
odoo_addons/sale_allotment/i18n/pt_BR.po
odoo_addons/sale_allotment/i18n/pt_PT.po
odoo_addons/sale_allotment/i18n/ro.po
odoo_addons/sale_allotment/i18n/sale_allotment.pot
odoo_addons/sale_allotment/i18n/sk.po
odoo_addons/sale_allotment/i18n/sl.po
odoo_addons/sale_allotment/i18n/tr.po
odoo_addons/sale_allotment/i18n/tr_TR.po
odoo_addons/sale_allotment/i18n/zh_CN.po
odoo_addons/sale_allotment/models/__init__.py
odoo_addons/sale_allotment/models/procurement_order.py
odoo_addons/sale_allotment/models/stock_move.py
odoo_addons/sale_allotment/static/description/icon.png
odoo_addons/sale_allotment/tests/__init__.py
odoo_addons/sale_allotment/tests/test_allotment.py
odoo_addons/sale_allotment/views/sale_order_line_view.xml
