Metadata-Version: 2.0
Name: odoo8-addon-sale-allotment
Version: 8.0.1.1.0.99.dev20
Summary: Separate the shipment according to allotment partner
Home-page: http://www.Openies.com/
Author: Openies,Numérigraphe,Odoo Community Association (OCA)
Author-email: support@odoo-community.org
License: AGPL-3
Platform: UNKNOWN
Classifier: Programming Language :: Python
Classifier: Framework :: Odoo
Classifier: License :: OSI Approved :: GNU Affero General Public License v3
Requires-Python: ~=2.7
Requires-Dist: odoo (<9.0a,>=8.0a)
